blooming/__init__.py
blooming/blooming.py
blooming/commands_jnpr.py
blooming/dev_parser.py
blooming/image_upgrade.py
blooming/l2ng_conf_parser.py
blooming/l2ng_testcase.py
blooming/test.py
blooming-1.0.8.dist-info/METADATA
blooming-1.0.8.dist-info/RECORD
blooming-1.0.8.dist-info/WHEEL
blooming-1.0.8.dist-info/entry_points.txt
blooming-1.0.8.dist-info/top_level.txt
