Metadata-Version: 2.1
Name: blooming
Version: 1.0.8
Summary: A(nother) test automation framework for network device.
Home-page: https://github.com/luxebeng/blooming
Author: Luxebeng
Author-email: luxebeng@gmail.com
License: BSD
Download-URL: https://github.com/luxebeng/blooming/tarball/1.0.8
Platform: UNKNOWN
Classifier: Development Status :: 3 - Alpha
Classifier: Intended Audience :: Developers
Classifier: Programming Language :: Python :: 3
Requires-Dist: coverage
Requires-Dist: docopt
Requires-Dist: nose
Requires-Dist: paramiko
Requires-Dist: pypi-publisher
Requires-Dist: sphinx
Requires-Dist: sphinx-rtd-theme
